amt_augpy/__init__.py
amt_augpy/add_pauses.py
amt_augpy/config.py
amt_augpy/convertfiles.py
amt_augpy/create_maestro_csv.py
amt_augpy/distortionchorus.py
amt_augpy/main.py
amt_augpy/pitch_shift.py
amt_augpy/reverbfilter.py
amt_augpy/time_stretch.py
amt_augpy/validate_split.py
amt_augpy1_0-1.0.8.dist-info/LICENSE
amt_augpy1_0-1.0.8.dist-info/METADATA
amt_augpy1_0-1.0.8.dist-info/WHEEL
amt_augpy1_0-1.0.8.dist-info/entry_points.txt
amt_augpy1_0-1.0.8.dist-info/top_level.txt
amt_augpy1_0-1.0.8.dist-info/RECORD
