Metadata-Version: 2.1
Name: amt-augpy1.0
Version: 1.0.8
Summary: Python augmentation toolkit for Automatic Music Transcription datasets
Author-email: Lars Monstad <lars.monstad@gmail.com>
License: MIT License
Project-URL: Homepage, https://github.com/LarsMonstad/amt-augpy
Project-URL: Issues, https://github.com/LarsMonstad/amt-augpy/issues
Classifier: Programming Language :: Python :: 3
Classifier: License :: OSI Approved :: MIT License
Classifier: Operating System :: OS Independent
Requires-Python: <3.12,>=3.8
License-File: LICENSE
Requires-Dist: librosa<1.0.0,>=0.9.1
Requires-Dist: numpy<2.0.0,>=1.23.5
Requires-Dist: soundfile>=0.12.1
Requires-Dist: pedalboard>=0.7.3
Requires-Dist: pretty-midi>=0.2.10
Requires-Dist: tqdm>=4.64.1
Requires-Dist: numba>=0.56.4
Requires-Dist: llvmlite>=0.39.1
Requires-Dist: pyyaml>=5.1.0
Provides-Extra: dev
Requires-Dist: pytest>=7.0.0; extra == "dev"
Requires-Dist: mypy>=1.0.0; extra == "dev"
Requires-Dist: black>=23.0.0; extra == "dev"
Requires-Dist: pylint>=2.15.0; extra == "dev"
Requires-Dist: sphinx>=6.0.0; extra == "dev"
Requires-Dist: types-PyYAML>=5.4.0; extra == "dev"
Requires-Dist: types-tqdm>=4.64.0; extra == "dev"
